{
    "fluentMethods": true,
    "relationships": [
        {
            "relationshipType": "one-to-one",
            "relationshipName": "usuario",
            "otherEntityName": "usuario",
            "otherEntityField": "nome",
            "ownerSide": true,
            "otherEntityRelationshipName": "secretaria"
        },
        {
            "relationshipType": "many-to-one",
            "relationshipName": "escola",
            "otherEntityName": "escola",
            "otherEntityField": "id"
        }
    ],
    "fields": [],
    "changelogDate": "20171022200919",
    "javadoc": "Entidade Usuario Secretaria da Escola",
    "entityTableName": "secretaria",
    "dto": "no",
    "pagination": "pagination",
    "service": "no"
}